[{"Name":"Markdown","Bytes":0,"Lines":0,"Code":0,"Comment":0,"Blank":0,"Complexity":0,"Count":1,"WeightedComplexity":0,"Files":[{"Language":"Markdown","PossibleLanguages":["Markdown"],"Filename":"README.md","Extension":"md","Location":"scc-tmp-path/README.md","Content":"","Bytes":0,"Lines":0,"Code":0,"Comment":0,"Blank":0,"Complexity":0,"WeightedComplexity":0,"Hash":null,"Callback":null,"Binary":false}]},{"Name":"Makefile","Bytes":0,"Lines":1553,"Code":812,"Comment":474,"Blank":267,"Complexity":8,"Count":19,"WeightedComplexity":0,"Files":[{"Language":"Makefile","PossibleLanguages":["Makefile"],"Filename":"Makefile","Extension":"","Location":"scc-tmp-path/Makefile","Content":null,"Bytes":798,"Lines":43,"Code":20,"Comment":16,"Blank":7,"Complexity":3,"WeightedComplexity":0,"Hash":null,"Callback":null,"Binary":false},{"Language":"Makefile","PossibleLanguages":["Makefile"],"Filename":"Makefile","Extension":"h","Location":"scc-tmp-path/src/Test_factory/AlignTest_newpFile_GPU/Makefile","Content":null,"Bytes":3435,"Lines":79,"Code":34,"Comment":31,"Blank":14,"Complexity":0,"WeightedComplexity":0,"Hash":null,"Callback":null,"Binary":false},{"Language":"Makefile","PossibleLanguages":["Makefile"],"Filename":"Makefile","Extension":"cu","Location":"scc-tmp-path/src/Test_factory/AlignTest_GPU/Makefile","Content":null,"Bytes":3417,"Lines":79,"Code":34,"Comment":31,"Blank":14,"Complexity":0,"WeightedComplexity":0,"Hash":null,"Callback":null,"Binary":false},{"Language":"Makefile","PossibleLanguages":["Makefile"],"Filename":"Makefile","Extension":"h","Location":"scc-tmp-path/src/Test_factory/Test_GPU/Makefile","Content":null,"Bytes":3407,"Lines":79,"Code":34,"Comment":31,"Blank":14,"Complexity":0,"WeightedComplexity":0,"Hash":null,"Callback":null,"Binary":false},{"Language":"Makefile","PossibleLanguages":["Makefile"],"Filename":"Makefile","Extension":"h","Location":"scc-tmp-path/src/Test_factory/Makefile","Content":null,"Bytes":1343,"Lines":39,"Code":21,"Comment":9,"Blank":9,"Complexity":0,"WeightedComplexity":0,"Hash":null,"Callback":null,"Binary":false},{"Language":"Makefile","PossibleLanguages":["Makefile"],"Filename":"Makefile","Extension":"h","Location":"scc-tmp-path/src/Test_factory/Test_CPU/Makefile","Content":null,"Bytes":1259,"Lines":40,"Code":21,"Comment":8,"Blank":11,"Complexity":0,"WeightedComplexity":0,"Hash":null,"Callback":null,"Binary":false},{"Language":"Makefile","PossibleLanguages":["Makefile"],"Filename":"common_cuda.mk","Extension":"mk","Location":"scc-tmp-path/src/common_cuda.mk","Content":null,"Bytes":6121,"Lines":150,"Code":66,"Comment":63,"Blank":21,"Complexity":0,"WeightedComplexity":0,"Hash":null,"Callback":null,"Binary":false},{"Language":"Makefile","PossibleLanguages":["Makefile"],"Filename":"Makefile","Extension":"cu","Location":"scc-tmp-path/src/KNN_factory/thrustKNN_GPU/Makefile","Content":null,"Bytes":3673,"Lines":82,"Code":34,"Comment":32,"Blank":16,"Complexity":0,"WeightedComplexity":0,"Hash":null,"Callback":null,"Binary":false},{"Language":"Makefile","PossibleLanguages":["Makefile"],"Filename":"Makefile","Extension":"cpp","Location":"scc-tmp-path/src/ParaKNN_factory/Makefile","Content":null,"Bytes":1355,"Lines":39,"Code":21,"Comment":9,"Blank":9,"Complexity":0,"WeightedComplexity":0,"Hash":null,"Callback":null,"Binary":false},{"Language":"Makefile","PossibleLanguages":["Makefile"],"Filename":"Makefile","Extension":"h","Location":"scc-tmp-path/src/KNN_factory/Makefile","Content":null,"Bytes":1293,"Lines":38,"Code":21,"Comment":8,"Blank":9,"Complexity":0,"WeightedComplexity":0,"Hash":null,"Callback":null,"Binary":false},{"Language":"Makefile","PossibleLanguages":["Makefile"],"Filename":"Makefile","Extension":"h","Location":"scc-tmp-path/src/ParaKNN_factory/AlignParaKNN_GPU/Makefile","Content":null,"Bytes":3382,"Lines":81,"Code":34,"Comment":30,"Blank":17,"Complexity":0,"WeightedComplexity":0,"Hash":null,"Callback":null,"Binary":false},{"Language":"Makefile","PossibleLanguages":["Makefile"],"Filename":"Makefile","Extension":"cpp","Location":"scc-tmp-path/src/Test_factory/AlignTest_CPU/Makefile","Content":null,"Bytes":1269,"Lines":40,"Code":21,"Comment":8,"Blank":11,"Complexity":0,"WeightedComplexity":0,"Hash":null,"Callback":null,"Binary":false},{"Language":"Makefile","PossibleLanguages":["Makefile"],"Filename":"common_flags.mk","Extension":"mk","Location":"scc-tmp-path/src/common_flags.mk","Content":null,"Bytes":10735,"Lines":385,"Code":284,"Comment":58,"Blank":43,"Complexity":4,"WeightedComplexity":0,"Hash":null,"Callback":null,"Binary":false},{"Language":"Makefile","PossibleLanguages":["Makefile"],"Filename":"ROOTDIR.mk","Extension":"mk","Location":"scc-tmp-path/src/ROOTDIR.mk","Content":null,"Bytes":544,"Lines":12,"Code":3,"Comment":8,"Blank":1,"Complexity":0,"WeightedComplexity":0,"Hash":null,"Callback":null,"Binary":false},{"Language":"Makefile","PossibleLanguages":["Makefile"],"Filename":"Makefile","Extension":"h","Location":"scc-tmp-path/src/Makefile","Content":null,"Bytes":1887,"Lines":88,"Code":41,"Comment":28,"Blank":19,"Complexity":1,"WeightedComplexity":0,"Hash":null,"Callback":null,"Binary":false},{"Language":"Makefile","PossibleLanguages":["Makefile"],"Filename":"Makefile","Extension":"h~","Location":"scc-tmp-path/src/Train_factory/AlignTrain_newpFile_GPU/Makefile","Content":null,"Bytes":3437,"Lines":79,"Code":34,"Comment":31,"Blank":14,"Complexity":0,"WeightedComplexity":0,"Hash":null,"Callback":null,"Binary":false},{"Language":"Makefile","PossibleLanguages":["Makefile"],"Filename":"Makefile","Extension":"h","Location":"scc-tmp-path/src/Train_factory/Makefile","Content":null,"Bytes":1347,"Lines":39,"Code":21,"Comment":9,"Blank":9,"Complexity":0,"WeightedComplexity":0,"Hash":null,"Callback":null,"Binary":false},{"Language":"Makefile","PossibleLanguages":["Makefile"],"Filename":"Makefile","Extension":"cpp","Location":"scc-tmp-path/src/Train_factory/AlignTrain_GPU/Makefile","Content":null,"Bytes":3419,"Lines":79,"Code":34,"Comment":31,"Blank":14,"Complexity":0,"WeightedComplexity":0,"Hash":null,"Callback":null,"Binary":false},{"Language":"Makefile","PossibleLanguages":["Makefile"],"Filename":"Makefile","Extension":"h","Location":"scc-tmp-path/src/shared/Makefile","Content":null,"Bytes":3506,"Lines":82,"Code":34,"Comment":33,"Blank":15,"Complexity":0,"WeightedComplexity":0,"Hash":null,"Callback":null,"Binary":false}]},{"Name":"C Header","Bytes":0,"Lines":1015,"Code":532,"Comment":265,"Blank":218,"Complexity":3,"Count":26,"WeightedComplexity":0,"Files":[{"Language":"C Header","PossibleLanguages":["C Header"],"Filename":"AlignTest_newpFile_GPU.h","Extension":"h","Location":"scc-tmp-path/src/Test_factory/AlignTest_newpFile_GPU/AlignTest_newpFile_GPU.h","Content":null,"Bytes":1025,"Lines":46,"Code":25,"Comment":12,"Blank":9,"Complexity":0,"WeightedComplexity":0,"Hash":null,"Callback":null,"Binary":false},{"Language":"C Header","PossibleLanguages":["C Header"],"Filename":"AlignTest_GPU.h","Extension":"h","Location":"scc-tmp-path/src/Test_factory/AlignTest_GPU/AlignTest_GPU.h","Content":null,"Bytes":935,"Lines":44,"Code":23,"Comment":12,"Blank":9,"Complexity":0,"WeightedComplexity":0,"Hash":null,"Callback":null,"Binary":false},{"Language":"C Header","PossibleLanguages":["C Header"],"Filename":"Test_implementation.h","Extension":"h","Location":"scc-tmp-path/src/Test_factory/Test_implementation.h","Content":null,"Bytes":480,"Lines":19,"Code":10,"Comment":6,"Blank":3,"Complexity":0,"WeightedComplexity":0,"Hash":null,"Callback":null,"Binary":false},{"Language":"C Header","PossibleLanguages":["C Header"],"Filename":"ITest.h","Extension":"h","Location":"scc-tmp-path/src/Test_factory/ITest.h","Content":null,"Bytes":852,"Lines":39,"Code":25,"Comment":6,"Blank":8,"Complexity":0,"WeightedComplexity":0,"Hash":null,"Callback":null,"Binary":false},{"Language":"C Header","PossibleLanguages":["C Header"],"Filename":"Test_GPU.h","Extension":"h","Location":"scc-tmp-path/src/Test_factory/Test_GPU/Test_GPU.h","Content":null,"Bytes":834,"Lines":42,"Code":21,"Comment":12,"Blank":9,"Complexity":0,"WeightedComplexity":0,"Hash":null,"Callback":null,"Binary":false},{"Language":"C Header","PossibleLanguages":["C Header"],"Filename":"IKNN.h","Extension":"h","Location":"scc-tmp-path/src/KNN_factory/IKNN.h","Content":null,"Bytes":957,"Lines":40,"Code":28,"Comment":6,"Blank":6,"Complexity":0,"WeightedComplexity":0,"Hash":null,"Callback":null,"Binary":false},{"Language":"C Header","PossibleLanguages":["C Header"],"Filename":"thrustKNN_GPU.h","Extension":"h","Location":"scc-tmp-path/src/KNN_factory/thrustKNN_GPU/thrustKNN_GPU.h","Content":null,"Bytes":2465,"Lines":94,"Code":57,"Comment":14,"Blank":23,"Complexity":0,"WeightedComplexity":0,"Hash":null,"Callback":null,"Binary":false},{"Language":"C Header","PossibleLanguages":["C Header"],"Filename":"thrustKNN_GPU_kernel.h","Extension":"h","Location":"scc-tmp-path/src/KNN_factory/thrustKNN_GPU/thrustKNN_GPU_kernel.h","Content":null,"Bytes":886,"Lines":31,"Code":17,"Comment":6,"Blank":8,"Complexity":0,"WeightedComplexity":0,"Hash":null,"Callback":null,"Binary":false},{"Language":"C Header","PossibleLanguages":["C Header"],"Filename":"KNN_implementation.h","Extension":"h","Location":"scc-tmp-path/src/KNN_factory/KNN_implementation.h","Content":null,"Bytes":404,"Lines":14,"Code":6,"Comment":6,"Blank":2,"Complexity":0,"WeightedComplexity":0,"Hash":null,"Callback":null,"Binary":false},{"Language":"C Header","PossibleLanguages":["C Header"],"Filename":"ParaKNN_factory.h","Extension":"h","Location":"scc-tmp-path/src/ParaKNN_factory/ParaKNN_factory.h","Content":null,"Bytes":414,"Lines":18,"Code":9,"Comment":6,"Blank":3,"Complexity":0,"WeightedComplexity":0,"Hash":null,"Callback":null,"Binary":false},{"Language":"C Header","PossibleLanguages":["C Header"],"Filename":"IParaKNN.h","Extension":"h","Location":"scc-tmp-path/src/ParaKNN_factory/IParaKNN.h","Content":null,"Bytes":764,"Lines":40,"Code":23,"Comment":6,"Blank":11,"Complexity":0,"WeightedComplexity":0,"Hash":null,"Callback":null,"Binary":false},{"Language":"C Header","PossibleLanguages":["C Header"],"Filename":"Test_CPU.h","Extension":"h","Location":"scc-tmp-path/src/Test_factory/Test_CPU/Test_CPU.h","Content":null,"Bytes":822,"Lines":41,"Code":20,"Comment":12,"Blank":9,"Complexity":0,"WeightedComplexity":0,"Hash":null,"Callback":null,"Binary":false},{"Language":"C Header","PossibleLanguages":["C Header"],"Filename":"KNN_factory.h","Extension":"h","Location":"scc-tmp-path/src/KNN_factory/KNN_factory.h","Content":null,"Bytes":610,"Lines":24,"Code":12,"Comment":7,"Blank":5,"Complexity":0,"WeightedComplexity":0,"Hash":null,"Callback":null,"Binary":false},{"Language":"C Header","PossibleLanguages":["C Header"],"Filename":"ParaKNN_implementation.h","Extension":"h","Location":"scc-tmp-path/src/ParaKNN_factory/ParaKNN_implementation.h","Content":null,"Bytes":351,"Lines":19,"Code":9,"Comment":6,"Blank":4,"Complexity":0,"WeightedComplexity":0,"Hash":null,"Callback":null,"Binary":false},{"Language":"C Header","PossibleLanguages":["C Header"],"Filename":"AlignParaKNN_GPU.h","Extension":"h","Location":"scc-tmp-path/src/ParaKNN_factory/AlignParaKNN_GPU/AlignParaKNN_GPU.h","Content":null,"Bytes":576,"Lines":33,"Code":15,"Comment":9,"Blank":9,"Complexity":0,"WeightedComplexity":0,"Hash":null,"Callback":null,"Binary":false},{"Language":"C Header","PossibleLanguages":["C Header"],"Filename":"AlignTest_CPU.h","Extension":"h","Location":"scc-tmp-path/src/Test_factory/AlignTest_CPU/AlignTest_CPU.h","Content":null,"Bytes":882,"Lines":42,"Code":21,"Comment":12,"Blank":9,"Complexity":0,"WeightedComplexity":0,"Hash":null,"Callback":null,"Binary":false},{"Language":"C Header","PossibleLanguages":["C Header"],"Filename":"Test_factory.h","Extension":"h","Location":"scc-tmp-path/src/Test_factory/Test_factory.h","Content":null,"Bytes":664,"Lines":27,"Code":12,"Comment":6,"Blank":9,"Complexity":0,"WeightedComplexity":0,"Hash":null,"Callback":null,"Binary":false},{"Language":"C Header","PossibleLanguages":["C Header"],"Filename":"runopt.h","Extension":"h","Location":"scc-tmp-path/src/runopt.h","Content":null,"Bytes":2651,"Lines":84,"Code":47,"Comment":21,"Blank":16,"Complexity":0,"WeightedComplexity":0,"Hash":null,"Callback":null,"Binary":false},{"Language":"C Header","PossibleLanguages":["C Header"],"Filename":"Train_implementation.h","Extension":"h","Location":"scc-tmp-path/src/Train_factory/Train_implementation.h","Content":null,"Bytes":490,"Lines":19,"Code":10,"Comment":6,"Blank":3,"Complexity":0,"WeightedComplexity":0,"Hash":null,"Callback":null,"Binary":false},{"Language":"C Header","PossibleLanguages":["C Header"],"Filename":"ITrain.h","Extension":"h","Location":"scc-tmp-path/src/Train_factory/ITrain.h","Content":null,"Bytes":947,"Lines":41,"Code":27,"Comment":7,"Blank":7,"Complexity":0,"WeightedComplexity":0,"Hash":null,"Callback":null,"Binary":false},{"Language":"C Header","PossibleLanguages":["C Header"],"Filename":"Train_factory.h","Extension":"h","Location":"scc-tmp-path/src/Train_factory/Train_factory.h","Content":null,"Bytes":546,"Lines":26,"Code":10,"Comment":6,"Blank":10,"Complexity":0,"WeightedComplexity":0,"Hash":null,"Callback":null,"Binary":false},{"Language":"C Header","PossibleLanguages":["C Header"],"Filename":"AlignTrain_newpFile_GPU.h","Extension":"h","Location":"scc-tmp-path/src/Train_factory/AlignTrain_newpFile_GPU/AlignTrain_newpFile_GPU.h","Content":null,"Bytes":1027,"Lines":46,"Code":24,"Comment":14,"Blank":8,"Complexity":0,"WeightedComplexity":0,"Hash":null,"Callback":null,"Binary":false},{"Language":"C Header","PossibleLanguages":["C Header"],"Filename":"AlignTrain_GPU.h","Extension":"h","Location":"scc-tmp-path/src/Train_factory/AlignTrain_GPU/AlignTrain_GPU.h","Content":null,"Bytes":937,"Lines":44,"Code":22,"Comment":14,"Blank":8,"Complexity":0,"WeightedComplexity":0,"Hash":null,"Callback":null,"Binary":false},{"Language":"C Header","PossibleLanguages":["C Header"],"Filename":"config.h","Extension":"h","Location":"scc-tmp-path/src/config.h","Content":null,"Bytes":1657,"Lines":62,"Code":17,"Comment":34,"Blank":11,"Complexity":0,"WeightedComplexity":0,"Hash":null,"Callback":null,"Binary":false},{"Language":"C Header","PossibleLanguages":["C Header"],"Filename":"common.h","Extension":"h","Location":"scc-tmp-path/src/shared/common.h","Content":null,"Bytes":852,"Lines":44,"Code":28,"Comment":4,"Blank":12,"Complexity":2,"WeightedComplexity":0,"Hash":null,"Callback":null,"Binary":false},{"Language":"C Header","PossibleLanguages":["C Header"],"Filename":"common_cuda.h","Extension":"h","Location":"scc-tmp-path/src/shared/common_cuda.h","Content":null,"Bytes":912,"Lines":36,"Code":14,"Comment":15,"Blank":7,"Complexity":1,"WeightedComplexity":0,"Hash":null,"Callback":null,"Binary":false}]},{"Name":"C++","Bytes":0,"Lines":887,"Code":635,"Comment":118,"Blank":134,"Complexity":116,"Count":10,"WeightedComplexity":0,"Files":[{"Language":"C++","PossibleLanguages":["C++"],"Filename":"Test_factory.cpp","Extension":"cpp","Location":"scc-tmp-path/src/Test_factory/Test_factory.cpp","Content":null,"Bytes":1224,"Lines":37,"Code":17,"Comment":12,"Blank":8,"Complexity":1,"WeightedComplexity":0,"Hash":null,"Callback":null,"Binary":false},{"Language":"C++","PossibleLanguages":["C++"],"Filename":"Test_CPU.cpp","Extension":"cpp","Location":"scc-tmp-path/src/Test_factory/Test_CPU/Test_CPU.cpp","Content":null,"Bytes":3848,"Lines":141,"Code":103,"Comment":12,"Blank":26,"Complexity":5,"WeightedComplexity":0,"Hash":null,"Callback":null,"Binary":false},{"Language":"C++","PossibleLanguages":["C++"],"Filename":"ParaKNN_factory.cpp","Extension":"cpp","Location":"scc-tmp-path/src/ParaKNN_factory/ParaKNN_factory.cpp","Content":null,"Bytes":629,"Lines":27,"Code":15,"Comment":6,"Blank":6,"Complexity":0,"WeightedComplexity":0,"Hash":null,"Callback":null,"Binary":false},{"Language":"C++","PossibleLanguages":["C++"],"Filename":"KNN_factory.cpp","Extension":"cpp","Location":"scc-tmp-path/src/KNN_factory/KNN_factory.cpp","Content":null,"Bytes":1147,"Lines":35,"Code":16,"Comment":12,"Blank":7,"Complexity":1,"WeightedComplexity":0,"Hash":null,"Callback":null,"Binary":false},{"Language":"C++","PossibleLanguages":["C++"],"Filename":"AlignParaKNN_GPU.cpp","Extension":"cpp","Location":"scc-tmp-path/src/ParaKNN_factory/AlignParaKNN_GPU/AlignParaKNN_GPU.cpp","Content":null,"Bytes":1710,"Lines":76,"Code":60,"Comment":5,"Blank":11,"Complexity":7,"WeightedComplexity":0,"Hash":null,"Callback":null,"Binary":false},{"Language":"C++","PossibleLanguages":["C++"],"Filename":"AlignTest_CPU.cpp","Extension":"cpp","Location":"scc-tmp-path/src/Test_factory/AlignTest_CPU/AlignTest_CPU.cpp","Content":null,"Bytes":3856,"Lines":151,"Code":115,"Comment":12,"Blank":24,"Complexity":12,"WeightedComplexity":0,"Hash":null,"Callback":null,"Binary":false},{"Language":"C++","PossibleLanguages":["C++"],"Filename":"Train_factory.cpp","Extension":"cpp","Location":"scc-tmp-path/src/Train_factory/Train_factory.cpp","Content":null,"Bytes":1178,"Lines":34,"Code":16,"Comment":12,"Blank":6,"Complexity":1,"WeightedComplexity":0,"Hash":null,"Callback":null,"Binary":false},{"Language":"C++","PossibleLanguages":["C++"],"Filename":"runopt.cpp","Extension":"cpp","Location":"scc-tmp-path/src/runopt.cpp","Content":null,"Bytes":8751,"Lines":306,"Code":242,"Comment":30,"Blank":34,"Complexity":86,"WeightedComplexity":0,"Hash":null,"Callback":null,"Binary":false},{"Language":"C++","PossibleLanguages":["C++"],"Filename":"common.cpp","Extension":"cpp","Location":"scc-tmp-path/src/shared/common.cpp","Content":null,"Bytes":867,"Lines":44,"Code":34,"Comment":1,"Blank":9,"Complexity":3,"WeightedComplexity":0,"Hash":null,"Callback":null,"Binary":false},{"Language":"C++","PossibleLanguages":["C++"],"Filename":"main.cpp","Extension":"cpp","Location":"scc-tmp-path/src/main.cpp","Content":null,"Bytes":959,"Lines":36,"Code":17,"Comment":16,"Blank":3,"Complexity":0,"WeightedComplexity":0,"Hash":null,"Callback":null,"Binary":false}]}]